{
  "project_info": {
    "project_number": "757546676633",
    "project_id": "todofirebase-2557e",
    "storage_bucket": "todofirebase-2557e.appspot.com"
  },
  "client": [
    {
      "client_info": {
        "mobilesdk_app_id": "1:757546676633:android:90e00a23628cb33057a308",
        "android_client_info": {
          "package_name": "com.example.todo_firebase"
        }
      },
      "oauth_client": [
        {
          "client_id": "757546676633-73ifjnahb35crnqctgsolj6fsoj50dmv.apps.googleusercontent.com",
          "client_type": 3
        }
      ],
      "api_key": [
        {
          "current_key": "AIzaSyAAjWgSZ6QJSIwPSdJWIuRCzYzF_ByIF8g"
        }
      ],
      "services": {
        "appinvite_service": {
          "other_platform_oauth_client": [
            {
              "client_id": "757546676633-73ifjnahb35crnqctgsolj6fsoj50dmv.apps.googleusercontent.com",
              "client_type": 3
            }
          ]
        }
      }
    }
  ],
  "configuration_version": "1"
}